Metadata-Version: 2.1
Name: alot-plugin-checkmail
Version: 0.0.15
Summary: Command wrapper with feedback for checking mail and other long-running tasks.
Home-page: https://github.com/tbjers/alot-plugin-checkmail
Author: Torgny Bjers
Author-email: torgny@bjers.org
License: UNKNOWN
Project-URL: Bug Tracker, https://github.com/tbjers/alot-plugin-checkmail/issues
Platform: UNKNOWN
Classifier: Programming Language :: Python :: 3
Classifier: License :: OSI Approved :: MIT License
Classifier: Operating System :: OS Independent
Provides: alot_checkmail
Requires-Python: >=3.6
License-File: LICENSE
